README.md
setup.cfg
setup.py
src/endemic/__init__.py
src/endemic.egg-info/PKG-INFO
src/endemic.egg-info/SOURCES.txt
src/endemic.egg-info/dependency_links.txt
src/endemic.egg-info/requires.txt
src/endemic.egg-info/top_level.txt
src/endemic/db/__init__.py
src/endemic/db/mysql/__init__.py
src/endemic/db/mysql/orm.py
src/endemic/db/redis/__init__.py
src/endemic/db/redis/orm.py
src/endemic/google/__init__.py
src/endemic/google/sheets.py
src/endemic/logging/__init__.py
src/endemic/logging/interface.py
src/endemic/logging/email/__init__.py
src/endemic/logging/email/logger.py
src/endemic/logging/fluentd/__init__.py
src/endemic/logging/fluentd/logger.py
src/endemic/logging/slack/__init__.py
src/endemic/logging/telegram/__init__.py
src/endemic/logging/telegram/logger.py
src/endemic/rabbit/__init__.py
src/endemic/rabbit/constant.py
src/endemic/rabbit/instance.py
src/endemic/rabbit/message.py
src/endemic/rabbit/parser.py
tests/test_db_mysql_orm.py
tests/test_db_redis_orm.py
tests/test_logging_email_logger.py
tests/test_logging_fluentd_logger.py
tests/test_logging_telegram_logger.py
tests/test_rabbit_instance.py
tests/test_rabbit_message.py
tests/test_rabbit_parser.py
tests/test_transform.py