Metadata-Version: 2.1
Name: endemic
Version: 0.1.17
Summary: Endemic misc class
Home-page: 
Author: Dima Denisov
Author-email: python@endemic.ru
License: MIT
Classifier: License :: OSI Approved :: MIT License
Classifier: Programming Language :: Python :: 3
Classifier: Programming Language :: Python :: 3.7
